{
    "AX": {
        "error": 0.008801058161276916,
        "error_type": "SEM",
        "filter_outliers_dict": {
            "filter_outliers": true,
            "iterations": 1,
            "std_devs": 2
        },
        "fit": "average",
        "value": 0.028593758496377086
    },
    "CDD": {
        "error": 7.927350970559077e-06,
        "error_type": "SEM",
        "filter_outliers_dict": {
            "filter_outliers": true,
            "iterations": 1,
            "std_devs": 10
        },
        "fit": "average",
        "value": 2.0625179943489735e-05
    },
    "H1": {
        "error": 0.007141048000649212,
        "error_type": "SEM",
        "filter_outliers_dict": {
            "filter_outliers": true,
            "iterations": 1,
            "std_devs": 2
        },
        "fit": "average",
        "value": 0.014584554864103549
    },
    "H2": {
        "error": 0.037079740179748626,
        "error_type": "SEM",
        "filter_outliers_dict": {
            "filter_outliers": true,
            "iterations": 1,
            "std_devs": 2
        },
        "fit": "average",
        "value": -0.6461160339037032
    },
    "L1": {
        "error": 0.0035922320692389808,
        "error_type": "SEM",
        "filter_outliers_dict": {
            "filter_outliers": true,
            "iterations": 1,
            "std_devs": 2
        },
        "fit": "average",
        "value": 0.018021283604369675
    },
    "L2": {
        "error": 0.0047262484569421895,
        "error_type": "SEM",
        "filter_outliers_dict": {
            "filter_outliers": true,
            "iterations": 1,
            "std_devs": 2
        },
        "fit": "average",
        "value": -0.0447100120406972
    }
}